MANIFEST.in
README.md
VERSION
setup.py
docs/source/description.rst
shu.egg-info/PKG-INFO
shu.egg-info/SOURCES.txt
shu.egg-info/dependency_links.txt
shu.egg-info/entry_points.txt
shu.egg-info/requires.txt
shu.egg-info/top_level.txt
src/shu/__init__.py
src/shu/adapters.py
src/shu/api.py
src/shu/interactions.py
src/shu/plugin.py
src/shu/resources.py
src/shu/wrappers.py