Metadata-Version: 1.1
Name: shu
Version: 0.1.0
Summary: 
Home-page: https://gitlab.com/greenhousegroup/ai/libraries/shu/
Author: Greenhouse AI team
Author-email: ai@greenhousegroup.com
License: UNKNOWN
Keywords: airflow,api,rest
Platform: UNKNOWN
Classifier: Programming Language :: Python :: 3
Classifier: License :: OSI Approved :: MIT License
Classifier: Operating System :: OS Independent
Classifier: Programming Language :: Python :: 3
